{
  "title": "animal",
  "dedication": "To my Brother",
  "recipient": {
    "name": "ahmad",
    "relationship": "Brother",
    "age": "14",
    "occasion": "Graduation",
    "customOccasion": ""
  },
  "character": {
    "mainCharacter": "Leo",
    "characterName": "Leo the Brave",
    "age": "12",
    "skinTone": "Light",
    "hairColor": "Brown",
    "accessories": "Glasses"
  },
  "characters": [
    {
      "characterTrait": "Curious & Brave",
      "physicalAppearance": "Wears a dark blue cloak with silver stars"
    },
    {
      "characterTrait": "Brave, Curious, Kind",
      "physicalAppearance": "Wears a dark blue cloak with silver stars"
    }
  ],
  "storyDescription": "Leo discovers a hidden portal in his backyard that leads to a world of talking animals and magical quests.",
  "generatedStory": "Title: Leo the Brave and the Enchanted Portal\n\nOnce upon a time, in a cozy little town called Willow Creek, there lived a boy named Leo the Brave. Leo was a curious and adventurous twelve-year-old who loved exploring the woods behind his house. He was known for his bravery and his signature dark blue cloak adorned with silver stars that shimmered in the sunlight.\n\nOne sunny afternoon, while wandering through the tall trees in his backyard, Leo stumbled upon a peculiar stone hidden beneath a tangle of vines. As he brushed away the leaves, he discovered a shimmering portal glowing with a mysterious light. Without hesitation, Leo bravely stepped through the portal and found himself in a magical world unlike anything he had ever seen.\n\nBefore him stood a lush forest filled with talking animals of all shapes and sizes. Birds chirped melodious tunes, rabbits hopped playfully, and squirrels chattered excitedly. Leo's eyes widened in amazement as he realized he had entered a world where animals were not only intelligent but also capable of speech.\n\nA wise old owl named Ollie approached Leo and greeted him warmly. \"Welcome, young traveler,\" Ollie hooted. \"You have entered the Enchanted Forest, a realm of magic and wonder. Are you here to embark on a quest?\"\n\nLeo's heart raced with excitement. \"Yes, I am ready for any adventure that comes my way,\" he declared, his voice filled with determination.\n\nOllie nodded approvingly and explained that a powerful sorcerer had cast a dark spell over the Enchanted Forest, causing chaos and despair among the animals. Leo, with his brave spirit and curious mind, was chosen to help break the curse and restore peace to the land.\n\nTogether with a brave fox named Fiona and a mischievous raccoon named Rascal, Leo set off on a quest to find the three magical gems needed to break the sorcerer's spell. Along the way, they encountered challenges and obstacles that tested Leo's courage and quick thinking.\n\nThrough forests and mountains, across rivers and valleys, Leo and his newfound friends persevered, overcoming every obstacle with bravery and determination. Finally, after many trials and tribulations, they reached the sorcerer's castle, where the final showdown awaited them.\n\nWith the power of friendship and courage, Leo and his companions defeated the sorcerer and shattered the curse that had plagued the Enchanted Forest. The animals rejoiced, grateful for Leo's bravery and"
}